sphinxcontrib_toc-1.0.0-py3.8-nspkg.pth
sphinxcontrib/toc.py
sphinxcontrib_toc-1.0.0.dist-info/METADATA
sphinxcontrib_toc-1.0.0.dist-info/WHEEL
sphinxcontrib_toc-1.0.0.dist-info/namespace_packages.txt
sphinxcontrib_toc-1.0.0.dist-info/top_level.txt
sphinxcontrib_toc-1.0.0.dist-info/RECORD
