Metadata-Version: 2.1
Name: sphinxcontrib-toc
Version: 1.0.0
Summary: Sphinx extension to allow .toc file to builde the Table of Contents
Home-page: https://github.com/tk0miya/sphinxcontrib-toc
Author: Takeshi KOMIYA
Author-email: i.tkomiya@gmail.com
License: BSD
Platform: any
Classifier: Development Status :: 4 - Beta
Classifier: Environment :: Console
Classifier: Framework :: Sphinx :: Extension
Classifier: Intended Audience :: Developers
Classifier: License :: OSI Approved :: BSD License
Classifier: Operating System :: OS Independent
Classifier: Programming Language :: Python
Classifier: Programming Language :: Python :: 3
Classifier: Programming Language :: Python :: 3.5
Classifier: Topic :: Documentation
Classifier: Topic :: Documentation :: Sphinx
Requires-Dist: Sphinx (>=2.0)
